CythonManager/__init__.py
CythonManager/conf/__init__.py
CythonManager/conf/templates/__init__.py
CythonManager/conf/templates/setup.py
CythonManager/core/__init__.py
CythonManager/core/managment/__init__.py
CythonManager/core/managment/commands/__init__.py
CythonManager/core/managment/commands/build.py
cython_manager-0.0.1.data/scripts/cython-manager.py
cython_manager-0.0.1.dist-info/METADATA
cython_manager-0.0.1.dist-info/RECORD
cython_manager-0.0.1.dist-info/WHEEL
cython_manager-0.0.1.dist-info/entry_points.txt
cython_manager-0.0.1.dist-info/top_level.txt
