Metadata-Version: 2.1
Name: cython-manager
Version: 0.0.1
Summary: UNKNOWN
Home-page: UNKNOWN
Author: Alexey Makridenko
Author-email: makridenko.a@yandex.ru
License: UNKNOWN
Platform: UNKNOWN
Requires-Dist: cython
